pyscenario/__init__.py
pyscenario/client.py
pyscenario/config_schema.py
pyscenario/const.py
pyscenario/ifsei.py
pyscenario/manager.py
pyscenario-0.1.10.dist-info/METADATA
pyscenario-0.1.10.dist-info/WHEEL
pyscenario-0.1.10.dist-info/licenses/LICENSE
pyscenario-0.1.10.dist-info/RECORD
