Metadata-Version: 2.4
Name: pyscenario
Version: 0.1.10
Summary: Python Scenario Automation contains a library to interface with Scenario IFSEI Classic for home automation.
License: Apache-2.0
License-File: LICENSE
Author: Carlos Mazzei
Author-email: carlos.mazzei@gmail.com
Requires-Python: >=3.12,<4.0
Classifier: Development Status :: 2 - Pre-Alpha
Classifier: License :: OSI Approved :: Apache Software License
Classifier: Programming Language :: Python :: 3
Classifier: Programming Language :: Python :: 3.12
Classifier: Programming Language :: Python :: 3.13
Classifier: Programming Language :: Python :: 3.14
Requires-Dist: asyncio (>=3.4.3,<5.0.0)
Requires-Dist: pyyaml (>=6.0.1,<7.0.0)
Requires-Dist: telnetlib3 (>=2.0.4,<3.0.0)
Requires-Dist: voluptuous (>=0.13.1,<0.17.0)
Project-URL: Documentation, https://pyscenario.readthedocs.io
Project-URL: Homepage, https://github.com/carlosmazzei/pyscenario
Project-URL: Repository, https://github.com/carlosmazzei/pyscenario
